{"odb_dov": {"Organizace, řízení a kontrola provozu svěřeného pracoviště s ohledem na zajištění optimální produktivity práce": 4, "Orientace v pravidlech a platných technologických postupech týkajících se poštovní přepravy nebo poštovního provozu": 3, "Řešení a odstraňování nepravidelností": 4, "Navrhování opatření k zajištění kvality poštovního provozu": 4, "Kontrola technologické kázně": 4, "Řízení a koordinace činností v oddělení nebo odboru": 4, "Zabezpečení výkonu přepravní činnosti": 4}, "odb_zna": {"poštovní předpisy, ceníky, poštovní tajemství": 4, "poštovní provoz, druhy poštovních zásilek a poštovních služeb": 4, "organizace poštovní přepravy": 0, "spojový zeměpis": 0}}