{"odb_dov": {"Dohled nad prováděním revizí a zkoušek technické způsobilosti technických zařízení z hlediska předepsané jakosti a kvality": 7, "Orientace v normách jakosti a kvality v hutní výrobě": 7, "Zpracování plánů řízení jakosti nových výrobků a procesů v hutní výrobě": 7, "Stanovování způsobů hodnocení a třídění jakosti a přejímacích podmínek v hutní výrobě": 7, "Metodické řízení vstupní, výstupní a mezioperační kontroly v hutní výrobě": 7, "Koordinace řízení jakosti, normalizace a zkušebnictví v hutní výrobě": 7, "Zjišťování příčin snížené kvality hutních výrobků a navrhování opatření k dosažení žádoucí kvality": 7, "Vyhodnocování systémů řízení jakosti v organizaci hutní výroby": 7, "Koordinace zpracování technickoekonomických studií, rozborů a prognóz jakosti v hutní výrobě": 7, "Metodické řízení normalizace, metrologie a zkušebnictví v hutní výrobě": 7}, "odb_zna": {"ekonomika a řízení ve strojírenství a kovovýrobě": 0, "technické kreslení ve strojírenství a v kovovýrobě": 4, "kovové materiály a slitiny a jejich vlastnosti (např. tvrdost, pružnost, houževnatost aj.)": 7, "technologie výroby oceli": 7, "technologie slévárenství": 0, "systémy a standardy jakosti a kvality ve strojírenství a kovovýrobě": 7, "zásady BOZP": 0, "automatizované systémy řízení výroby": 0}}