{"odb_dov": {"Kontrola dodržování technologických postupů a bezpečnostních předpisů ve stavebnictví": 4, "Vedení jednotlivých zakázek od zadání až po realizaci": 4, "Najímání, výběr a řízení dodavatelů služeb i řemeslných prací": 4, "Provozní kontrola konstrukce, funkce a připojení topidel na komín, posuzování topidel z hlediska požární ochrany": 4, "Analýza zadání individuálně stavěného topidla": 4, "Vypracování technické dokumentace individuálně stavěného topidla": 4, "Technická příprava stavby individuálních topidel": 4, "Čtení a používání technických podkladů – výkresů, návodů a pracovních postupů": 4, "Dimenzování a navrhování individuálně stavěných lokálních topidel na pevná paliva - kachlových kamen a sporáků a krbů": 4, "Organizace realizace stavby individuálně stavěného topidla": 4, "Obchodní jednání s klientem a subdodavateli": 4, "Vypracování protokolu o výpočtu parametrů individuálně stavěného topidla": 4}, "odb_zna": {"technické kreslení ve stavebnictví": 4, "žáruvzdorné stavební a keramické materiály": 4, "technologie zednických prací": 0, "technologie obkladačských prací": 0, "technologie kamnářských prací": 4, "komerční právo, smluvně-závazkové vztahy, obchodní společnosti, obchodní zákoník": 4, "konstruování a tvorba technické dokumentace pomocí počítače (CAD aj.)": 4, "konstrukční a technologická řešení individuálně stavěných topidel": 4, "materiály pro stavbu individuálně stavěných topidel": 4, "bezpečnost práce, požární ochrana a hygiena práce související s kamnářskými pracemi": 4}}