{"odb_dov": {"Dodržování technologií mlékárenských výrob": 3, "Obsluha strojů a zařízení pro zpracování mléka na mlékárenské výrobky": 3, "Odběr vzorků při zpracování mléka a smyslové posuzování jejich jakosti": 3, "Posuzování hodnot kvality surovin a parametrů výrobního procesu při zpracování mléka": 3, "Měření základních chemicko-fyzikálních veličin v mlékárenském provozu": 3, "Skladování polotovarů, přísad a hotových mléčných výrobků": 3, "Dodržování sanitačních postupů, provádění hygienicko-sanitační činnosti v mlékárenském provozu": 3, "Dodržování bezpečnostních předpisů a zásad bezpečnosti potravin v mlékárenské výrobě; bezpečné používání čisticích prostředků a jiných chemikálií": 3}, "odb_zna": {"technologie zpracování mléka a výroba mléčných výrobků": 3, "systémy a standardy jakosti a kvality v potravinářství": 0, "zásady BOZP": 3}}