{"odb_dov": {"Dodržování zásad bezpečnosti a prevence úrazů": 4, "Poskytování první pomoci dítěti/dětem": 5, "Péče o běžně nemocné dítě v domácím ošetřování": 4, "Vedení dítěte k hygienickým návykům": 4, "Uplatňování zásad správného životního stylu podle věku dítěte": 4, "Uplatňování metod a forem pedagogické práce s ohledem na věk dítěte/dětí": 4, "Řešení nepříznivých výchovných situací z pedagogicko-psychologického hlediska": 5, "Uplatňování znalostí o vývojových etapách a socializaci dítěte v praxi": 4, "Dodržování etických principů při práci chůvy a vedení dítěte k morálním hodnotám": 4, "Orientace v pracovněprávních vztazích uplatnitelných v profesním životě chůvy": 4, "Provozní a hygienická pravidla při práci s dětmi v zařízení či domácnosti dítěte": 4}, "odb_zna": {"zdraví a hygiena při práci": 4, "základy pracovního práva, zákoník práce": 4, "ošetřovatelská péče o kojence": 4, "ošetřovatelská péče o děti": 4, "první pomoc": 4, "obecná pedagogika": 4, "předškolní vzdělávání a výchova": 0}, "obecne": {"Počítačová způsobilost": 2, "": 0, "Numerická způsobilost": 2, "Ekonomické povědomí": 1, "Právní povědomí": 2, "Jazyková způsobilost v češtině": 2}, "mekke": {"Efektivní komunikace": 4, "Kooperace (spolupráce)": 3, "Kreativita": 3, "Flexibilita": 4, "Uspokojování zákaznických potřeb": 4, "Výkonnost": 3, "Samostatnost": 4, "Řešení problémů": 3, "Plánování a organizování práce": 3, "Celoživotní učení": 3, "Aktivní přístup": 4, "Zvládání zátěže": 3, "Objevování a orientace v informacích": 3, "Vedení lidí (leadership)": 3, "Ovlivňování ostatních": 3}}