{"odb_dov": {"Vyhodnocování provozuschopnosti energetických výrobních a rozvodných zařízení a navrhování opatření ke snížení poruchovosti": 7, "Plánování a příprava preventivních prohlídek, revizí a údržby rozvodných zařízení": 7, "Provádění technického dozoru na energetických pracovištích": 7, "Kontrola a posuzování technických, provozních a ekonomických parametrů výroby energie a rozhodování o potřebných zásazích": 7, "Používání technické dokumentace a norem při práci na elektrotechnických a elektronických zařízeních": 7, "Zpracování koncepcí, metodik a prognóz rozvoje v teplárenství": 7, "Řešení rozvoje systémů, výrobních a rozvodných zařízení v teplárenství": 7, "Řízení prací mistrů na vymezeném energetickém úseku": 7, "Řízení energetických provozů": 7, "Obsluha řízení provozu a kontrola činnosti úseků v teplárnách, redukčních a výměníkových stanicích": 7}, "odb_zna": {"druhy energie, jejich přenos, využívání, ztráty, účinnost": 7, "zařízení a systémy pro výrobu a rozvod tepla a jejich provoz": 7, "zařízení a systémy pro výrobu elektrické energie a jejich provoz": 7, "systémy a standardy jakosti a kvality v energetice": 7, "elektrotechnika": 7, "metody hodnocení spotřeby energie a řízení této spotřeby": 7, "měření provozních veličin": 7, "zařízení a systémy pro rozvod energie a jejich provoz": 7, "bezpečnost práce a požární ochrana": 7, "předpisy a technické normy v energetice": 7}}