{"odb_dov": {"Poznávání taxonů květin": 3, "Kultivační práce": 3, "Sklizeň, třídění, skladování a expedice různých skupin květin a jejich úprava pro prodej": 3, "Rozmnožování květin": 3, "Aplikace ochranných prostředků proti chorobám a škůdcům okrasných rostlin": 3, "Řízení a obsluha traktorů a jiné mechanizace": 3, "Výsadba a ošetřování různých skupin a taxonů květin během vegetace ve venkovních podmínkách i krytých prostorách": 3}, "odb_zna": {"květinářství": 3, "botanika": 3, "realizace a údržba zeleně": 3, "ekonomika, řízení a plánování v zahradnické produkci": 0}}