{"odb_dov": {"Operativní řešení organizačních a provozních problémů při nákupu, dopravě a expedici dříví": 7, "Určování optimálního využívání výrobních a pracovních kapacit": 7, "Stanovování harmonogramů nasazování a využívání prostředků k dopravě a manipulaci dříví": 7, "Optimální volba sortimentace a kvality surového dříví": 7, "Vyřizování a přijímání objednávek na přepravu a určování řidičů a vozidel k jejich provedení": 7, "Uzavírání obchodních smluv v lesním hospodářství": 7, "Zpracování objednávek, kupních smluv a nabídek": 7, "Provádění operativních změn kalkulací a cen podle vývoje nákladů": 7, "Vedení příslušné dokumentace a evidence používaných prostředků a zařízení": 7}, "odb_zna": {"silniční doprava - technicko organizační zabezpečení": 7, "ekonomika, plánování, řízení a obchodní činnost v lesním hospodářství": 7, "sortimentace dříví": 7, "cenové analýzy, cenová politika, stanovení ceny": 7, "obchodní vyjednávání": 7, "lesní doprava a mechanizace": 7}, "obecne": {"Počítačová způsobilost": 3, "Způsobilost k řízení osobního automobilu": 2, "Numerická způsobilost": 3, "Ekonomické povědomí": 3, "Právní povědomí": 3, "Jazyková způsobilost v češtině": 3, "Jazyková způsobilost v angličtině": 2, "Jazyková způsobilost v dalším cizím jazyce": 1}, "mekke": {"Efektivní komunikace": 5, "Kooperace (spolupráce)": 4, "Kreativita": 3, "Flexibilita": 4, "Uspokojování zákaznických potřeb": 5, "Výkonnost": 5, "Samostatnost": 5, "Řešení problémů": 5, "Plánování a organizování práce": 5, "Celoživotní učení": 4, "Aktivní přístup": 4, "Zvládání zátěže": 4, "Objevování a orientace v informacích": 3, "Vedení lidí (leadership)": 4, "Ovlivňování ostatních": 4}}