{"odb_dov": {"Získávání nových klientů banky a obchodních partnerů": 7, "Zpracovávání strategie, politiky a plánu obchodů s cennými papíry na úseku investičního bankovnictví": 7, "Kontrola průběhu celého obchodu až do jeho konečného vypořádání": 7, "Provádění vlastních analýz vývoje na kapitálových trzích včetně jejich interpretace": 7, "Příprava podkladů a dokladů potřebných pro uskutečňování složitých obchodů na kapitálových trzích": 7, "Vedení požadované dokumentace (o uskutečněných obchodech, o klientech apod.)": 7, "Zjišťování a vyhledávání informací o vývoji na finančních a kapitálových trzích v tuzemsku i v zahraničí": 7, "Zpracovávání propagačních materiálů o vývoji na kapitálových trzích, o jeho vlivu na jednotlivé produkty apod.": 7, "Poskytování komplexní poradenské a konzultační služby pro klienty v oblasti kapitálových trhů": 7, "Projednávání nejsložitějších obchodů v oblasti cenných papírů s klienty i s ostatními účastníky tohoto obchodu": 7, "Zajišťování realizace nejsložitějších obchodů s cennými papíry dle požadavků klientů a v souladu s platnými předpisy": 7, "Zajišťování trvalého přímého kontaktu s českými i zahraničními kapitálovými trhy": 7}, "odb_zna": {"pravidla evidování korespondence, smluv a dalších dokumentů": 4, "bankovnictví obecně a bankovní služby": 7, "bankovní controlling": 7, "mezinárodní bankovnictví": 7, "finanční trhy, makléřská činnost": 7, "základní principy obchodování s cennými papíry": 7, "kapitálové trhy, makléřská činnost": 7, "investiční bankovnictví": 7, "právo v oblasti finančních a kapitálových trhů": 7, "klientela a potenciální klientela, péče o ni": 0}, "obecne": {}, "mekke": {}}