{"odb_dov": {"Volba postupu práce, pomůcek a náhradních dílů pro provádění oprav a oživování elektronických přístrojů, zařízení a systémů, včetně výpočetní techniky": 4, "Kontrola stavu a fungování elektronických přístrojů, zařízení a systémů, včetně výpočetní techniky": 4, "Diagnostikování poruch elektronických přístrojů, zařízení a systémů, včetně výpočetní techniky": 4, "Sestavování, montáž, zapojování a oživování elektronických obvodů, přístrojů, zařízení a systémů, včetně výpočetní techniky": 4, "Opravy elektronických přístrojů, zařízení a systémů, včetně výpočetní techniky": 4, "Cejchování přístrojů měřicí a automatizační techniky": 4, "Ruční obrábění a zpracovávání kovových materiálů": 4, "Měření elektrických veličin a parametrů, vyhodnocování naměřených hodnot": 4}, "odb_zna": {"vysílací, telekomunikační, radiokomunikační a další spojovací zařízení a systémy": 4, "počítačový hardware": 4, "zdravotnické elektronické přístroje a zařízení": 4, "elektrotechnika": 4, "elektrotechnické materiály, vodiče, kabely": 4, "technické kreslení v elektrotechnice": 4, "měření elektrických veličin": 4, "elektrické stroje a přístroje": 4, "elektronika obecně": 4, "elektronické prvky": 4, "elektronické a číslicové obvody": 4, "spotřební elektronika (televize, videa, CD přehrávače, pračky apod.)": 4, "časoměrné přístroje a zařízení": 4}, "obecne": {"Počítačová způsobilost": 3, "Numerická způsobilost": 2, "Ekonomické povědomí": 1, "Jazyková způsobilost v češtině": 2, "Jazyková způsobilost v angličtině": 1}, "mekke": {"Kooperace (spolupráce)": 2, "Flexibilita": 3, "Samostatnost": 3, "Řešení problémů": 3, "Celoživotní učení": 3, "Objevování a orientace v informacích": 2}}