{"odb_dov": {"Orientace v sortimentu textilních materiálů a výrobků": 3, "Příjem prádla a oděvů pro prádelnu": 3, "Volba technologického postupu praní prádla a oděvů": 3, "Praní prádla a oděvů": 3, "Odvodňování a odstřeďování prádla a oděvů": 3, "Sušení prádla a oděvů": 3, "Rozvolňování a žehlení rovného prádla": 3, "Žehlení tvarového prádla a oděvů": 3, "Zprostředkování opravy a úpravy prádla a oděvů": 3, "Balení a uskladnění čistého prádla a oděvů v meziskladu": 3, "Expedice čistého prádla a oděvů": 3, "Dodržování zásad bezpečnosti a ochrany zdraví při práci v provozech prádelen a čistíren": 3, "Provádění hygienicko-sanitační činnosti v prádelenských provozech a dodržování hygienických předpisů": 3}, "odb_zna": {"bezpečnost práce": 3, "zdraví a hygiena při práci": 3, "technologie detašování": 0, "technologie praní, odvodňování, sušení a rozvolňování prádla a oděvů": 3, "technologie žehlení, mandlování a tvarování prádla a oděvů": 3, "prací a pomocné prostředky pro úpravu textilu": 0, "textilní materiály a produkty, druhy, vlastnosti, vady, způsoby rozborů a zkoušek": 3}, "obecne": {"Počítačová způsobilost": 1, "": 0, "Numerická způsobilost": 2, "Ekonomické povědomí": 2, "Právní povědomí": 1, "Jazyková způsobilost v češtině": 2}, "mekke": {"Efektivní komunikace": 3, "Kooperace (spolupráce)": 3, "Kreativita": 3, "Flexibilita": 3, "Uspokojování zákaznických potřeb": 3, "Výkonnost": 3, "Samostatnost": 3, "Řešení problémů": 3, "Plánování a organizování práce": 3, "Celoživotní učení": 2, "Aktivní přístup": 3, "Zvládání zátěže": 3, "Objevování a orientace v informacích": 1, "": 0, "Ovlivňování ostatních": 2}}