{"odb_dov": {"Obsluha a údržba přiděleného zbraňového systému": 4, "Obsluha a údržba přidělené zbraně": 4, "Plnění úkolů v úkolových uskupeních, v bojových podmínkách a v zahraničních vojenských operacích": 4, "Vykonávání dozorčí a strážní služby": 4, "Vedení boje se zbraní nebo zbraňovým systémem samostatně nebo v sestavě vojenské jednotky vyplývající z rozsahu příslušného služebního místa": 4, "Plnění úkolů při vojenském výcviku, odborné přípravě a vzdělávání": 4, "Obsluha a údržba vojenské výzbroje a výstroje": 4, "Vedení podřízených k bojové a morální připravenosti a vojenskému vystupování": 4, "Řízení a vedení výcviku a odborné přípravy vojáků": 4, "Plnění úkolů, zajišťování a výkon odborných činností vyplývajících z vojenské hodnosti rotného, vojenské odbornosti a zařazení na služebním místě": 4, "Obsluha, údržba a opravy speciální vojenské techniky": 4, "Obsluha, údržba a opravy speciálních vojenských technických zařízení": 4, "Opravy vojenské výzbroje": 4}, "odb_zna": {"postupy při obsluze a údržbě zbraní nebo přidělených zbraňových systémů": 4, "vojenská taktika a strategie vyplývající z rozsahu příslušného služebního místa": 4, "první pomoc": 4, "vnitřní předpisy ozbrojených sil ČR": 4, "bezpečnost práce a požární ochrana": 4, "činnosti rotného ozbrojených sil ČR": 4, "postupy řízení a velení vyplývající ze služebního zařazení v ozbrojených silách ČR": 4, "postupy při obsluze a údržbě speciální vojenské techniky": 4, "postupy při obsluze a údržbě speciálních vojenských technických zařízení": 4, "postupy při vykonávání technických, speciálních a odborných činností v ozbrojených silách ČR": 4}}