{"odb_dov": {"Řízení technologického úseku kožedělné výroby": 6, "Stanovování komplexních technologických postupů a technických podmínek v celém rozsahu kožedělné výroby": 6, "Volba postupu práce, materiálů a technologických podmínek pro výrobu kožedělných výrobků": 6, "Stanovování výrobních zařízení pro kožedělnou výrobu": 6, "Vedení technické dokumentace kožedělné výroby": 6, "Zpracování technických podkladů o kožedělné výrobě pro marketingovou a obchodní činnost": 6, "Kontrola dodržování technologických postupů v kožedělné výrobě": 6, "Provádění technických zkoušek nové technologie v kožedělné výrobě": 6, "Orientace v normách a v technických podkladech v kožedělné výrobě": 6}, "odb_zna": {"kůže a usně, druhy, vlastnosti, vady, způsoby rozborů a zkoušek": 6, "technologie výroby galanterního (koženého) zboží": 6, "technologie koželužského zpracování kůže": 6, "technologie zpracování kožešin": 6, "ekonomika a řízení kožedělné a obuvnické výroby": 0, "systémy a standardy jakosti a kvality v obuvnictví a zpracování usní": 0, "materiály v obuvnictví (druhy, vlastnosti, vady, způsoby rozborů a zkoušek)": 6, "technologie výroby obuvi": 6, "technologie výroby komponent a polotovarů pro výrobu": 6}}