{"odb_dov": {"Zpracovávání koncepcí, metodik a prognóz rozvoje v energetice": 6, "Řešení rozvoje energetických systémů, výrobních a rozvodných zařízení": 6, "Plánování investičních procesů v oblasti energetických zařízení a systémů": 6, "Používání technické dokumentace a norem při práci na elektrotechnických a elektronických zařízeních": 6, "Analýza stavu a technických řešení energetických zařízení a distribuční elektrické sítě": 6}, "odb_zna": {"druhy energie, jejich přenos, využívání, ztráty, účinnost": 6, "systémy a standardy jakosti a kvality v energetice": 6, "elektrotechnika": 6, "venkovní elektrická vedení": 6, "trafostanice": 6, "zařízení a systémy pro rozvod elektrické energie a jejich provoz": 6, "bezpečnost práce a požární ochrana": 6, "dokumentace investičních záměrů v energetice": 6}, "obecne": {"Počítačová způsobilost": 3, "Numerická způsobilost": 3, "Ekonomické povědomí": 2, "Právní povědomí": 2, "Jazyková způsobilost v češtině": 3}, "mekke": {"Efektivní komunikace": 4, "Kooperace (spolupráce)": 4, "Samostatnost": 4, "Řešení problémů": 4, "Plánování a organizování práce": 4, "Objevování a orientace v informacích": 3}}