{"odb_dov": {"Kontrola dodržování úvěrových limitů": 6, "Zpracovávání analýz úvěrového portfolia": 6, "Příprava úvěrové dokumentace pro archivaci a následně pro skartaci": 6, "Spolupráce při přípravě dokumentace problémových úvěrů a při přípravě podkladů pro finanční audit": 6, "Provádění kontroly smluv jednotlivých aktivních úvěrových obchodů, a to z hlediska úplnosti dokumentace a věcné a formální správnosti včetně správných úrokových sazeb": 6, "Spolupráce při zpracováváni ekonomických analýz (výpočet dílčích ukazatelů)": 6, "Příprava a kompletace dokladů a podkladů pro uzavírání složitějších smluv o poskytnutí úvěrů": 6, "Poskytování konzultací a poradenské činnosti v oblasti správy úvěrového portfolia": 6, "Vyřizování dotazů soudů a orgánů zúčastněných v trestním a správním řízení": 6, "Spolupráce při vymáhání nesplácených úvěrů (složitější případy) s ostatními útvary peněžního ústavu": 6, "Vykonávání odborné lektorské činnosti v oblasti úvěrového portfolia": 0, "Vedení příslušných dokumentací a evidencí (přehledy o úvěrové angažovanosti klientů, evidence aktivních úvěrových obchodů, evidence uložené úvěrové dokumentace, evidence neplatičů splátek apod.)": 6, "Zpracovávání statistických výkazů a hlášení o úvěrovém portfoliu": 6}, "odb_zna": {"pravidla evidování korespondence, smluv a dalších dokumentů": 4, "bankovnictví obecně a bankovní služby": 6, "úvěrový obchod": 6, "bankovní účetnictví": 4, "bankovní controlling": 0, "postupy vymáhání pohledávek": 0, "klientela a potenciální klientela, péče o ni": 0}, "obecne": {}, "mekke": {}}