{"odb_dov": {"Vedení evidencí zbraní, střeliva a donucovacích prostředků": 7, "Vedení příslušné dokumentace v oblasti služební přípravy celníků": 7, "Poskytování rad a odborných konzultací v oblasti metodiky speciální přípravy celníků včetně jejich přípravy střelecké a v oblastech využívání zbraní a donucovacích prostředků": 7, "Zajišťování oprav poškozených či jinak nevyhovujících zbraní": 7, "Zajišťování služební tělesné, střelecké a taktické přípravy a přípravy k používání donucovacích prostředků": 7, "Provádění stanovených technických prohlídek zbraní": 7, "Koordinace činností v oblasti zbraní a donucovacích prostředků včetně střelecké a speciální přípravy celníků": 7}, "odb_zna": {"držení, nošení a používání střelných zbraní": 7}, "obecne": {}, "mekke": {}}