{"odb_dov": {"Přijímání zakázek ve střihové službě": 3, "Konstruování střihů dílů a součástí oděvů": 3, "Modelování základních střihů oděvů": 3, "Sestavování střihových poloh pro oddělování dílů a součástí oděvů": 3, "Oddělování jednotlivých dílů a součástí oděvů": 3, "Seřizování strojů pro oddělování dílů a součástí oděvů": 3, "Předávání zakázek ve střihové službě zákazníkům": 3, "Zaznamenávání údajů o pracovních postupech a výsledcích práce": 0, "Nakládání s odpadem při oddělování dílů a součástí oděvů": 0}, "odb_zna": {"techniky zhotovování střihů pro oděvy": 3, "textilní materiály a produkty, druhy, vlastnosti, technologie zpracování": 3, "kůže a usně, druhy, vlastnosti, vady, způsoby rozborů a zkoušek": 0, "kožešiny a usně, druhy, vlastnosti, vady": 0, "oděvní technologie": 0, "technické kreslení v textilu, oděvnictví nebo zpracování kožešin": 3}}