{"odb_dov": {"Vedení příslušné dokumentace v dobývání": 4, "Řízení hornických činností nebo činností prováděné hornickým způsobem": 4, "Řízení a organizace prací na vymezeném technologickém úseku na lomu nebo dolu": 4, "Zajišťování bezpečného a odborného řízení hornické činnosti nebo činnosti prováděné hornickým způsobem na vymezeném technologickém úseku": 4}, "odb_zna": {"technologie povrchového dobývání": 4, "bezpečnost v hornictví": 4, "ekonomika a řízení v hornictví": 2, "strojnictví, hornické stroje a zařízení": 4}, "obecne": {"Počítačová způsobilost": 2, "Způsobilost k řízení osobního automobilu": 2, "Numerická způsobilost": 2, "Ekonomické povědomí": 2, "Právní povědomí": 2, "Jazyková způsobilost v češtině": 2}, "mekke": {"Efektivní komunikace": 4, "Kooperace (spolupráce)": 4, "Kreativita": 3, "Flexibilita": 4, "Výkonnost": 4, "Samostatnost": 4, "Řešení problémů": 4, "Plánování a organizování práce": 4, "Celoživotní učení": 3, "Aktivní přístup": 4, "Zvládání zátěže": 3, "Objevování a orientace v informacích": 3, "Vedení lidí (leadership)": 3, "Ovlivňování ostatních": 3}}