{"odb_dov": {"Organizace, řízení a kontrola provozu svěřeného pracoviště s ohledem na zajištění optimální produktivity práce": 6, "Zapracovávání pracovníků do poštovního provozu": 5, "Vzdělávání pracovníků při zavádění nových poštovních produktů, technologických změnách apod.": 5, "Orientace v provozních předpisech a poštovních podmínkách, včetně znalosti BOZP": 3, "Kontrola a zajištění dodržování technologických postupů pošty": 5, "Kontrola poštovních zaměstnanců, technologické kázně, bezpečnosti osob a majetku": 5, "Řízení a koordinace činností podřízených pracovníků v poštovním provozu": 6, "Řešení organizačních a provozních problémů v logistickém centru nebo na poště": 6, "Vyřizování dotazů soudů, finančních úřadů a exekutorů": 6, "Řešení stížností a reklamací": 6, "Zpracování administrativní a personální agendy podřízených pracovníků": 5}, "odb_zna": {"poštovní předpisy, ceníky, poštovní tajemství": 6, "poštovní provoz, druhy poštovních zásilek a poštovních služeb": 6, "organizace poštovní přepravy": 0, "postupy automatizovaných poštovních technologií": 0, "spojový zeměpis": 0}, "obecne": {"Počítačová způsobilost": 2, "Způsobilost k řízení osobního automobilu": 2, "Numerická způsobilost": 2, "Ekonomické povědomí": 1, "Právní povědomí": 1, "Jazyková způsobilost v češtině": 2, "Jazyková způsobilost v angličtině": 1, "Jazyková způsobilost v dalším cizím jazyce": 1}, "mekke": {"Efektivní komunikace": 3, "Uspokojování zákaznických potřeb": 3, "Samostatnost": 3, "Řešení problémů": 3, "Plánování a organizování práce": 3, "Zvládání zátěže": 2, "Vedení lidí (leadership)": 3}}